LawAgent/__init__.py
LawAgent/module.py
LawAgent-0.0.1.dist-info/METADATA
LawAgent-0.0.1.dist-info/WHEEL
LawAgent-0.0.1.dist-info/top_level.txt
LawAgent-0.0.1.dist-info/RECORD
