Metadata-Version: 2.1
Name: LawAgent
Version: 0.0.1
Summary: AI Law Healthcare Comprehensive Repo
Author-email: aihubadmin@126.com
Project-URL: homepage, http://www.deepnlp.org
Project-URL: repository, https://github.com/AI-Hub-Admin/LawAgent
Keywords: API,Law,Legal,AI Agent
Classifier: Development Status :: 3 - Alpha
Classifier: Intended Audience :: Developers
Classifier: Topic :: Software Development :: Build Tools
Classifier: License :: OSI Approved :: MIT License
Requires-Python: >=3.4
